addition/__init__.py
addition/addition.py
divide/__init__.py
divide/divide.py
multiply/__init__.py
multiply/multiply.py
subtract/__init__.py
subtract/subtract.py
calculator_advanced-1.0.0.dist-info/LICENSE.txt
calculator_advanced-1.0.0.dist-info/METADATA
calculator_advanced-1.0.0.dist-info/WHEEL
calculator_advanced-1.0.0.dist-info/top_level.txt
calculator_advanced-1.0.0.dist-info/RECORD
