Metadata-Version: 2.1
Name: calculator-advanced
Version: 1.0.0
Summary: A simple Python package for calculation.
Home-page: https://github.com/1324aman/custom-python-package
Author: Aman Mourya
Author-email: aman.mourya.1003@gmail.com
License: UNKNOWN
Project-URL: bug_tracker, https://github.com/1324aman/custom-python-package/issues
Project-URL: repository, https://github.com/1324aman/custom-python-package
Platform: UNKNOWN
Classifier: Programming Language :: Python :: 3
Classifier: License :: OSI Approved :: MIT License
Classifier: Operating System :: OS Independent
Requires-Python: >=3.8
License-File: LICENSE.txt
